pike_kernel/__init__.py
pike_kernel/__main__.py
pike_kernel/install.py
pike_kernel/kernel.py
pike_kernel-0.0.1.dist-info/WHEEL
pike_kernel-0.0.1.dist-info/METADATA
pike_kernel-0.0.1.dist-info/RECORD
