Metadata-Version: 1.2
Name: pike_kernel
Version: 0.0.1
Summary: A Pike kernel for Jupyter
Home-page: https://github.com/kevinior/jupyter-pike-kernel
License: UNKNOWN
Author: Kevin O'Rourke
Author-email: kevin-pypi@caboose.org.uk
Classifier: License :: OSI Approved :: MIT License
Classifier: Framework :: IPython
Classifier: Programming Language :: Python :: 3
Classifier: Programming Language :: Pike
Requires-Dist: pexpect (>=4.0)
